CHANGELOG.rst
pyramid_blacksmith-5.1.0.dist-info/METADATA
pyramid_blacksmith-5.1.0.dist-info/WHEEL
pyramid_blacksmith-5.1.0.dist-info/entry_points.txt
pyramid_blacksmith-5.1.0.dist-info/licenses/LICENSE
pyramid_blacksmith/__init__.py
pyramid_blacksmith/adapters/__init__.py
pyramid_blacksmith/binding.py
pyramid_blacksmith/middleware.py
pyramid_blacksmith/middleware_factory.py
pyramid_blacksmith/py.typed
pyramid_blacksmith/typing.py
pyramid_blacksmith/utils.py
pyramid_blacksmith-5.1.0.dist-info/RECORD
