Metadata-Version: 2.1
Name: pyramid-blacksmith
Version: 5.1.0
Summary: Pyramid Bindings for Blacksmith
Author-Email: Guillaume Gauvrit <guillaume@gauvr.it>
License: MIT License
Classifier: Development Status :: 5 - Production/Stable
Classifier: Framework :: Pyramid
Classifier: Intended Audience :: Developers
Classifier: License :: OSI Approved :: MIT License
Classifier: Topic :: Software Development :: Libraries :: Python Modules
Classifier: Topic :: Internet :: WWW/HTTP
Classifier: Topic :: Software Development :: Libraries
Classifier: Topic :: System :: Networking
Classifier: Typing :: Typed
Project-URL: Homepage, https://github.com/mardiros/pyramid-blacksmith
Project-URL: Documentation, https://mardiros.github.io/pyramid-blacksmith
Project-URL: Repository, https://github.com/mardiros/pyramid-blacksmith.git
Project-URL: Issues, https://github.com/mardiros/pyramid-blacksmith/issues
Project-URL: Changelog, https://mardiros.github.io/pyramid-blacksmith/user/changelog.html
Requires-Python: >=3.10
Requires-Dist: blacksmith<6,>=5.0.0
Requires-Dist: pyramid<3,>1.10
Requires-Dist: prometheus-client<1,>=0.17
Provides-Extra: docs
Requires-Dist: sphinx>=7.0.0; extra == "docs"
Requires-Dist: sphinx-autodoc-typehints<2,>=1.12.0; extra == "docs"
Requires-Dist: furo>=2024.8.6; extra == "docs"
